phonepiece/__init__.py
phonepiece/allophone.py
phonepiece/arpa.py
phonepiece/articulatory.py
phonepiece/config.py
phonepiece/distance.py
phonepiece/edit_distance.py
phonepiece/epitran.py
phonepiece/inventory.py
phonepiece/ipa.py
phonepiece/iso.py
phonepiece/lang.py
phonepiece/lexicon.py
phonepiece/phone_tokenizer.py
phonepiece/phoneme.py
phonepiece/pinyin.py
phonepiece/segmenter.py
phonepiece/timit.py
phonepiece/transliterator.py
phonepiece/tree.py
phonepiece/unit.py
phonepiece/utils.py
phonepiece/bin/__init__.py
phonepiece/bin/download_model.py
phonepiece/bin/eval_distance.py
phonepiece/bin/info.py
phonepiece/bin/list_lang.py
phonepiece/bin/update_model.py
phonepiece/data/__init__.py
phonepiece/data/arpabet.csv
phonepiece/data/ipa-xsampa.csv
phonepiece/data/ipa_all.csv
phonepiece/data/ipa_base.csv
phonepiece/data/language.tsv
phonepiece/data/phoible-segments-features.tsv
phonepiece/data/pinyin2ipa.txt
phonepiece/data/tree.txt
phonepiece-1.4.2.dist-info/LICENSE.txt
phonepiece-1.4.2.dist-info/METADATA
phonepiece-1.4.2.dist-info/WHEEL
phonepiece-1.4.2.dist-info/top_level.txt
phonepiece-1.4.2.dist-info/RECORD
