Metadata-Version: 2.1
Name: phonepiece
Version: 1.4.2
Summary: a multilingual phone tokenizer
Home-page: https://github.com/xinjli/phonepiece
Author: Xinjian Li
Author-email: xinjianl@cs.cmu.edu
License: UNKNOWN
Platform: UNKNOWN
License-File: LICENSE.txt
Requires-Dist: epitran
Requires-Dist: panphon
Requires-Dist: ipapy
Requires-Dist: iso-639
Requires-Dist: editdistance
